sqlcon/__init__.py
sqlcon/lib.py
sqlcon/sqlcon.py
sqlcon-0.1.5.dist-info/LICENSE
sqlcon-0.1.5.dist-info/WHEEL
sqlcon-0.1.5.dist-info/METADATA
sqlcon-0.1.5.dist-info/RECORD
