Metadata-Version: 2.1
Name: sqlcon
Version: 0.1.5
Summary: Construct indented SQL from Python.
Home-page: https://github.com/tcorbettclark/sql-constructor
License: MIT
Keywords: SQL,indent,format,template,construct
Author: Timothy Corbett-Clark
Author-email: timothy.corbettclark@gmail.com
Requires-Python: >=3.6,<4.0
Classifier: License :: OSI Approved :: MIT License
Classifier: Programming Language :: Python :: 3
Classifier: Programming Language :: Python :: 3.6
Classifier: Programming Language :: Python :: 3.7
Classifier: Programming Language :: Python :: 3.8
